setup.py
odoo/addons/res_partner_api_somconnexio/README.rst
odoo/addons/res_partner_api_somconnexio/__init__.py
odoo/addons/res_partner_api_somconnexio/__manifest__.py
odoo/addons/res_partner_api_somconnexio/services/__init__.py
odoo/addons/res_partner_api_somconnexio/services/partner_email_change_process.py
odoo/addons/res_partner_api_somconnexio/services/partner_email_change_service.py
odoo/addons/res_partner_api_somconnexio/services/res_partner_service.py
odoo/addons/res_partner_api_somconnexio/services/schemas.py
odoo/addons/res_partner_api_somconnexio/tests/__init__.py
odoo/addons/res_partner_api_somconnexio/tests/services/__init__.py
odoo/addons/res_partner_api_somconnexio/tests/services/test_partner_email_change_service.py
odoo/addons/res_partner_api_somconnexio/tests/services/test_res_partner_service.py
odoo_addon_res_partner_api_somconnexio.egg-info/PKG-INFO
odoo_addon_res_partner_api_somconnexio.egg-info/SOURCES.txt
odoo_addon_res_partner_api_somconnexio.egg-info/dependency_links.txt
odoo_addon_res_partner_api_somconnexio.egg-info/not-zip-safe
odoo_addon_res_partner_api_somconnexio.egg-info/requires.txt
odoo_addon_res_partner_api_somconnexio.egg-info/top_level.txt